modflowapi/__init__.py
modflowapi/modflowapi.py
modflowapi/util.py
modflowapi/version.py
modflowapi/extensions/__init__.py
modflowapi/extensions/apiexchange.py
modflowapi/extensions/apimodel.py
modflowapi/extensions/apisimulation.py
modflowapi/extensions/data.py
modflowapi/extensions/pakbase.py
modflowapi/extensions/runner.py
modflowapi-0.2.0.dist-info/LICENSE
modflowapi-0.2.0.dist-info/METADATA
modflowapi-0.2.0.dist-info/WHEEL
modflowapi-0.2.0.dist-info/top_level.txt
modflowapi-0.2.0.dist-info/RECORD
