Metadata-Version: 2.1
Name: modflowapi
Version: 0.2.0
Summary: modflowapi is an extension to the xmipy Python package
Author-email: "Joseph D. Hughes" <jdhughes@usgs.gov>, Martijn Russcher <Martijn.Russcher@deltares.nl>, "Christian D. Langevin" <langevin@usgs.gov>, Julian Hofer <Julian.Hofer@deltares.nl>, "Joshua D. Larsen" <jlarsen@usgs.gov>
Maintainer-email: "Joseph D. Hughes" <jdhughes@usgs.gov>
License: CC0
Project-URL: Repository, https://github.com/MODFLOW-USGS/modflowapi
Project-URL: Publication, https://doi.org/10.1016/j.envsoft.2021.105257
Keywords: MODFLOW,groundwater,hydrogeology,bmi,xmi
Classifier: Intended Audience :: Science/Research
Classifier: License :: CC0 1.0 Universal (CC0 1.0) Public Domain Dedication
Classifier: Programming Language :: Python :: 3
Classifier: Programming Language :: Python :: 3 :: Only
Classifier: Programming Language :: Python :: 3.8
Classifier: Programming Language :: Python :: 3.9
Classifier: Programming Language :: Python :: 3.10
Classifier: Programming Language :: Python :: 3.11
Classifier: Topic :: Scientific/Engineering :: Hydrology
Requires-Python: >=3.8
License-File: LICENSE
Requires-Dist: numpy
Requires-Dist: pandas
Requires-Dist: xmipy
Provides-Extra: dev
Requires-Dist: modflowapi[lint,test] ; extra == 'dev'
Provides-Extra: lint
Requires-Dist: black ; extra == 'lint'
Requires-Dist: flake8 ; extra == 'lint'
Requires-Dist: isort ; extra == 'lint'
Requires-Dist: pylint ; extra == 'lint'
Provides-Extra: test
Requires-Dist: filelock ; extra == 'test'
Requires-Dist: modflow-devtools ; extra == 'test'
Requires-Dist: pytest ; extra == 'test'
Requires-Dist: pytest-order ; extra == 'test'
Requires-Dist: pytest-xdist ; extra == 'test'
